{
  "version": 3,
  "middleware": {
    "/": {
      "files": [
        "server/edge-runtime-webpack.js",
        "server/middleware.js"
      ],
      "name": "middleware",
      "page": "/",
      "matchers": [
        {
          "regexp": "^(?:\\/(_next\\/data\\/[^/]{1,}))?\\/admin(?:\\/((?:[^\\/#\\?]+?)(?:\\/(?:[^\\/#\\?]+?))*))?(.json)?[\\/#\\?]?$",
          "originalSource": "/admin/:path*"
        },
        {
          "regexp": "^(?:\\/(_next\\/data\\/[^/]{1,}))?\\/api(?:\\/((?:[^\\/#\\?]+?)(?:\\/(?:[^\\/#\\?]+?))*))?(.json)?[\\/#\\?]?$",
          "originalSource": "/api/:path*"
        },
        {
          "regexp": "^(?:\\/(_next\\/data\\/[^/]{1,}))?(?:\\/((?!_next\\/static|_next\\/image|favicon.ico).*))(.json)?[\\/#\\?]?$",
          "originalSource": "/((?!_next/static|_next/image|favicon.ico).*)"
        }
      ],
      "wasm": [],
      "assets": [],
      "env": {
        "__NEXT_BUILD_ID": "bOKRIovjHu_Zt_Xu-N_7X",
        "NEXT_SERVER_ACTIONS_ENCRYPTION_KEY": "AvQdcki8pT7PI9vauXCb28QrWpcROL4MxzKKReKeS0U=",
        "__NEXT_PREVIEW_MODE_ID": "8ced058af95ef1b9505a084d05eb5778",
        "__NEXT_PREVIEW_MODE_ENCRYPTION_KEY": "0d3937853614891abd2046ac2561379c55c7eece4999107dc81b23eda3413b7d",
        "__NEXT_PREVIEW_MODE_SIGNING_KEY": "3ace0caaa4866d66393f7ffb05d0d79ef4047f74c95afc097d886025c04f768e"
      }
    }
  },
  "functions": {},
  "sortedMiddleware": [
    "/"
  ]
}